ai_grams_pm/__init__.py
ai_grams_pm/queries_manager.py
ai_grams_pm-0.0.8.dist-info/METADATA
ai_grams_pm-0.0.8.dist-info/WHEEL
ai_grams_pm-0.0.8.dist-info/top_level.txt
ai_grams_pm-0.0.8.dist-info/RECORD
