Metadata-Version: 2.1
Name: ai-grams-pm
Version: 0.0.8
Summary: AI Grams' API manager for PM
Home-page: https://github.com/AIGrams/ai_grams_pm
Author: Antonio Briola
Author-email: aigrams.team@gmail.com
License: MIT
Download-URL: https://github.com/AIGrams/ai_grams_pm/archive/v0.0.8.tar.gz
Platform: UNKNOWN
Classifier: Development Status :: 4 - Beta
Classifier: Intended Audience :: Developers
Classifier: License :: OSI Approved :: MIT License
Classifier: Operating System :: POSIX :: Linux
Classifier: Programming Language :: Python :: 3.7
Classifier: Programming Language :: Python :: 3.8
Classifier: Programming Language :: Python :: 3.9
Requires-Dist: numpy
Requires-Dist: requests
